vsports/__init__.py
vsports/vsports.py
vsports-1.0.2.dist-info/LICENSE
vsports-1.0.2.dist-info/METADATA
vsports-1.0.2.dist-info/WHEEL
vsports-1.0.2.dist-info/top_level.txt
vsports-1.0.2.dist-info/RECORD
