Metadata-Version: 2.2
Name: vsports
Version: 1.0.2
Summary: A Python client for the VSports API
Home-page: https://github.com/sapo/vsports
Author: SAPO
Author-email: eduardo.pinto@gmail.com
Classifier: Programming Language :: Python :: 3
Classifier: License :: OSI Approved :: MIT License
Classifier: Operating System :: OS Independent
Requires-Python: >=3.10
License-File: LICENSE
Requires-Dist: requests
Requires-Dist: redis
Dynamic: author
Dynamic: author-email
Dynamic: classifier
Dynamic: description
Dynamic: description-content-type
Dynamic: home-page
Dynamic: requires-dist
Dynamic: requires-python
Dynamic: summary
